{
    "frames": {
        "battle_explosion_0": {
            "frame": {
                "x": 306,
                "y": 542,
                "w": 139,
                "h": 105
            },
            "rotated": false,
            "trimmed": false,
            "spriteSourceSize": {
                "x": 0,
                "y": 0,
                "w": 139,
                "h": 105
            },
            "sourceSize": {
                "w": 139,
                "h": 105
            }
        },
        "battle_explosion_1": {
            "frame": {
                "x": 0,
                "y": 182,
                "w": 180,
                "h": 178
            },
            "rotated": false,
            "trimmed": false,
            "spriteSourceSize": {
                "x": 0,
                "y": 0,
                "w": 180,
                "h": 178
            },
            "sourceSize": {
                "w": 180,
                "h": 178
            }
        },
        "battle_explosion_2": {
            "frame": {
                "x": 379,
                "y": 180,
                "w": 172,
                "h": 177
            },
            "rotated": false,
            "trimmed": false,
            "spriteSourceSize": {
                "x": 0,
                "y": 0,
                "w": 172,
                "h": 177
            },
            "sourceSize": {
                "w": 172,
                "h": 177
            }
        },
        "battle_explosion_3": {
            "frame": {
                "x": 562,
                "y": 0,
                "w": 172,
                "h": 174
            },
            "rotated": false,
            "trimmed": false,
            "spriteSourceSize": {
                "x": 0,
                "y": 0,
                "w": 172,
                "h": 174
            },
            "sourceSize": {
                "w": 172,
                "h": 174
            }
        },
        "battle_explosion_4": {
            "frame": {
                "x": 0,
                "y": 365,
                "w": 174,
                "h": 172
            },
            "rotated": false,
            "trimmed": false,
            "spriteSourceSize": {
                "x": 0,
                "y": 0,
                "w": 174,
                "h": 172
            },
            "sourceSize": {
                "w": 174,
                "h": 172
            }
        },
        "battle_explosion_5": {
            "frame": {
                "x": 0,
                "y": 0,
                "w": 192,
                "h": 177
            },
            "rotated": false,
            "trimmed": false,
            "spriteSourceSize": {
                "x": 0,
                "y": 0,
                "w": 192,
                "h": 177
            },
            "sourceSize": {
                "w": 192,
                "h": 177
            }
        },
        "battle_explosion_6": {
            "frame": {
                "x": 379,
                "y": 0,
                "w": 178,
                "h": 175
            },
            "rotated": false,
            "trimmed": false,
            "spriteSourceSize": {
                "x": 0,
                "y": 0,
                "w": 178,
                "h": 175
            },
            "sourceSize": {
                "w": 178,
                "h": 175
            }
        },
        "battle_explosion_7": {
            "frame": {
                "x": 156,
                "y": 542,
                "w": 145,
                "h": 118
            },
            "rotated": false,
            "trimmed": false,
            "spriteSourceSize": {
                "x": 0,
                "y": 0,
                "w": 145,
                "h": 118
            },
            "sourceSize": {
                "w": 145,
                "h": 118
            }
        },
        "battle_explosion_8": {
            "frame": {
                "x": 0,
                "y": 542,
                "w": 151,
                "h": 136
            },
            "rotated": false,
            "trimmed": false,
            "spriteSourceSize": {
                "x": 0,
                "y": 0,
                "w": 151,
                "h": 136
            },
            "sourceSize": {
                "w": 151,
                "h": 136
            }
        },
        "battle_explosion_9": {
            "frame": {
                "x": 344,
                "y": 365,
                "w": 156,
                "h": 142
            },
            "rotated": false,
            "trimmed": false,
            "spriteSourceSize": {
                "x": 0,
                "y": 0,
                "w": 156,
                "h": 142
            },
            "sourceSize": {
                "w": 156,
                "h": 142
            }
        },
        "battle_explosion_10": {
            "frame": {
                "x": 179,
                "y": 365,
                "w": 160,
                "h": 151
            },
            "rotated": false,
            "trimmed": false,
            "spriteSourceSize": {
                "x": 0,
                "y": 0,
                "w": 160,
                "h": 151
            },
            "sourceSize": {
                "w": 160,
                "h": 151
            }
        },
        "battle_explosion_11": {
            "frame": {
                "x": 562,
                "y": 353,
                "w": 166,
                "h": 162
            },
            "rotated": false,
            "trimmed": false,
            "spriteSourceSize": {
                "x": 0,
                "y": 0,
                "w": 166,
                "h": 162
            },
            "sourceSize": {
                "w": 166,
                "h": 162
            }
        },
        "battle_explosion_12": {
            "frame": {
                "x": 562,
                "y": 179,
                "w": 168,
                "h": 169
            },
            "rotated": false,
            "trimmed": false,
            "spriteSourceSize": {
                "x": 0,
                "y": 0,
                "w": 168,
                "h": 169
            },
            "sourceSize": {
                "w": 168,
                "h": 169
            }
        },
        "battle_explosion_13": {
            "frame": {
                "x": 197,
                "y": 183,
                "w": 172,
                "h": 175
            },
            "rotated": false,
            "trimmed": false,
            "spriteSourceSize": {
                "x": 0,
                "y": 0,
                "w": 172,
                "h": 175
            },
            "sourceSize": {
                "w": 172,
                "h": 175
            }
        },
        "battle_explosion_14": {
            "frame": {
                "x": 197,
                "y": 0,
                "w": 177,
                "h": 178
            },
            "rotated": false,
            "trimmed": false,
            "spriteSourceSize": {
                "x": 0,
                "y": 0,
                "w": 177,
                "h": 178
            },
            "sourceSize": {
                "w": 177,
                "h": 178
            }
        }
    },
    "meta": {
        "app": "https://github.com/Ensighten/spritesmith",
        "image": "battle_explosion.png",
        "format": "RGBA8888",
        "size": {
            "w": 734,
            "h": 678
        },
        "scale": 1
    }
}