{
	"standard":{
		"data":[
			[
				{ "filename": "f023_a043_snow_1.png" }
			], [
				{ "filename": "f023_a043_snow_2.png", "offset":[540,20] }
			]
		]
	},
	"standard_2":{
		"data":[
			[
				{ "filename": "f023_a043_snow_1.png" }
			], [
				{ "filename": "f023_a043_snow_3.png", "offset":[540,20] }
			]
		]
	},
	"standard_3":{
		"data":[
			[
				{ "filename": "f023_a043_snow_1.png" }
			], [
				{ "filename": "f023_a043_snow_4.png", "offset":[540,20] }
			]
		]
	},
	"standard_4": {
		"data":[
			[
				{ "filename": "f023_a043_snow_1.png" }
			]
		]
	},
	"case": {
		"time":[
			{ "time": "040000", "state": "standard_3" },
			{ "time": "100000", "state": "standard_2" },
			{ "time": "160000", "state": "standard_4" },
			{ "time": "220000", "state": "standard" }
		]
	},
	"reloadflag": true
}
